Workbook

Sheet Read me
B2: Work Copilot - Feature Inventory & Launch Scope Decisions
B3: Built from a read of the codebase at commit a4cf254 (main). Every row cites where the code lives.
B5: How to use this
C6: 1. Work down the 'Feature inventory' tab. The 'Proposed action' column is a recommendation, not a decision.
C7: 2. Put your call in the yellow 'YOUR DECISION' column (dropdown). It is the only column you need to fill in.
C8: 3. The 'Scope summary' tab counts your decisions live as you make them.
C9: 4. Anything marked 'Move to backup repo' should be cut to a separate private repository before the public repo goes live.
B11: Action key
B12: Keep - core | C12: Ships enabled in v1. Part of the core promise.
B13: Keep - flag off by default | C13: Code stays, hidden behind a feature flag. Available to power users, invisible on first run.
B14: Fix before launch | C14: Ships, but has a defect or gap that blocks launch as it stands.
B15: Extract to add-on | C15: Leaves core, ships as a separate plugin. Proves the extensibility USP.
B16: Move to backup repo | C16: Cut from the public repository entirely; preserved privately.
B17: Delete | C17: Remove outright. Dead, duplicated, or unsafe to publish.
B19: USP reference
B20: U1 | C20: Open source, bring your own API key - no vendor account, no lock-in
B21: U2 | C21: Extensible via add-on plugins, some of them ours
B22: U3 | C22: Organised AI chats - a page structure for your areas and projects, chats live inside pages
B23: U4 | C23: Atomic items - every action or statement is its own taggable, multi-filed object with canonical references
B24: U5 | C24: Page-scoped context plus a configurable mission for the install and for each page
B25: U6 | C25: The assistant co-authors into the corpus, creating a learning loop against your own protocols
B26: U7 | C26: No terminal, no code, no repo to manage - it all happens in a website
B28: Assumptions
C29: Feature list derived by reading the source, not from a product backlog - a feature with no code is not listed here.
C30: 'Effort to keep' is a judgement of ongoing maintenance burden (code size, external dependencies, coupling), not build cost.
C31: 'Launch risk' flags issues visible from reading the code. It is not a substitute for a QA pass or a security audit.
C32: Line counts and file paths are accurate as of the commit above and will drift as work proceeds.

Sheet Feature inventory
A1: ID | B1: Bundle | C1: Area | D1: Feature | E1: What it does | F1: Primary code location | G1: USP served | H1: Effort to keep | I1: Launch risk / known issue | J1: Proposed action | K1: Rationale | L1: YOUR DECISION | M1: Owner | N1: Notes
A2: 1 | B2: Core plugin | C2: Content model | D2: Items as native WP posts | E2: Atomic unit of the system - one task/idea/note per post. | F2: wp-copilot/includes/class-post-types.php | G2: U1, U4 | H2: Low | I2: None | J2: Keep - core | K2: The atomic-item USP. Non-negotiable.
A3: 2 | B3: Core plugin | C3: Content model | D3: Pages as contexts | E3: Native WP pages form the folder-like hierarchy for areas and projects. | F3: wp-copilot/includes/class-taxonomy-sync.php | G3: U3, U5 | H3: Low | I3: None | J3: Keep - core | K3: The organisation USP. Non-negotiable.
A4: 3 | B4: Core plugin | C4: Content model | D4: Headings CPT (wcp_heading) | E4: Sub-sections inside a page that group items without polluting the page tree. | F4: wp-copilot/includes/class-post-types.php | G4: U3, U4 | H4: Low | I4: None | J4: Keep - core | K4: Needed for page structure to be usable beyond a flat list.
A5: 4 | B5: Core plugin | C5: Content model | D5: wcp_context taxonomy + auto-sync | E5: Mirrors the page/heading tree into a hierarchical taxonomy; how items attach to structure. | F5: wp-copilot/includes/class-taxonomy-sync.php | G5: U3, U4 | H5: Med | I5: Sync can drift on bulk edits - needs a repair/verify pass | J5: Keep - core | K5: Load-bearing for everything. Verify sync integrity before launch.
A6: 5 | B6: Core plugin | C6: Content model | D6: Multi-context association | E6: One item can belong to several pages/headings at once. | F6: wp-copilot/includes/class-rest-api.php | G6: U4 | H6: Low | I6: None | J6: Keep - core | K6: This is what makes canonical references possible.
A7: 6 | B7: Core plugin | C7: Content model | D7: item_type taxonomy (task/info/learning/spec) | E7: Classifies what kind of atom each item is. | F7: wp-copilot/includes/class-taxonomies.php | G7: U4 | H7: Low | I7: 'spec' type is thinly used | J7: Keep - core | K7: Keep task/info/learning. Consider dropping 'spec' - it duplicates 'info' for most users.
A8: 7 | B8: Core plugin | C8: Content model | D8: priority taxonomy (critical/high/med/low) | E8: Priority ranking on items. | F8: wp-copilot/includes/class-taxonomies.php | G8: U4 | H8: Low | I8: None | J8: Keep - core | K8: Expected baseline for a work tool.
A9: 8 | B9: Core plugin | C9: Content model | D9: task_status taxonomy (to-do/in-progress/done) | E9: Workflow state for task items. | F9: wp-copilot/includes/class-taxonomies.php | G9: U4 | H9: Low | I9: None | J9: Keep - core | K9: Expected baseline.
A10: 9 | B10: Core plugin | C10: Content model | D10: spec_status taxonomy (draft/review/final) | E10: Workflow state for spec items only. | F10: wp-copilot/includes/class-taxonomies.php | G10: U4 | H10: Low | I10: Extra taxonomy for a rarely used item type | J10: Keep - flag off by default | K10: Adds a UI dropdown most users never touch. Ship hidden.
A11: 10 | B11: Core plugin | C11: Content model | D11: Pinned taxonomy | E11: Floats an item to the top of its page. | F11: wp-copilot/includes/class-taxonomies.php | G11: U4 | H11: Low | I11: None | J11: Keep - core | K11: Cheap, high-utility.
A12: 11 | B12: Core plugin | C12: Content model | D12: Freeform tags (native post_tag) | E12: Standard WP tags on items, with tag archive pages. | F12: wp-copilot/includes/class-taxonomies.php | G12: U4 | H12: Low | I12: None | J12: Keep - core | K12: Tagging is explicitly part of the atomic-item pitch.
A13: 12 | B13: Core plugin | C13: Content model | D13: Nested sub-items (post_parent outliner) | E13: Items nest to arbitrary depth and render as an indented outline. | F13: work-copilot-theme/functions.php (render_item_tree) | G13: U4 | H13: Med | I13: Deep nesting + context filters interact subtly | J13: Keep - core | K13: Needed for action plans to land as real structure.
... A130: 129 | B130: Repo tooling | C130: Docs | D130: AGENTS.md / claude.md / agent-os standards | E130: Coding standards and agent instructions for this repo. | F130: AGENTS.md, claude.md, agent-os/ | G130: - | H130: Low | I130: None | J130: Keep - core | K130: Useful signal to open-source contributors that the repo has standards.

Sheet Scope summary
B2: Scope summary
B3: Counts recalculate from the Feature inventory tab. 'Yours' stays at zero until you fill in the decision column.
B4: These cells are live formulas. They compute the moment the file opens in Excel, LibreOffice, Numbers or Google Sheets - if a preview shows them blank, that preview is not calculating, not a broken sheet.
B5: By proposed action
B6: Action | C6: Proposed | D6: Yours | E6: What it means for the launch
B7: Keep - core | C7: =COUNTIF('Feature inventory'!$J$2:$J$130,$B7) | D7: =COUNTIF('Feature inventory'!$L$2:$L$130,$B7) | E7: The v1 surface area a new user sees.
B8: Keep - flag off by default | C8: =COUNTIF('Feature inventory'!$J$2:$J$130,$B8) | D8: =COUNTIF('Feature inventory'!$L$2:$L$130,$B8) | E8: Code retained, hidden. Zero onboarding cost.
B9: Fix before launch | C9: =COUNTIF('Feature inventory'!$J$2:$J$130,$B9) | D9: =COUNTIF('Feature inventory'!$L$2:$L$130,$B9) | E9: Your pre-launch engineering backlog.
B10: Extract to add-on | C10: =COUNTIF('Feature inventory'!$J$2:$J$130,$B10) | D10: =COUNTIF('Feature inventory'!$L$2:$L$130,$B10) | E10: Separate plugins - and the proof that the platform is extensible.
B11: Move to backup repo | C11: =COUNTIF('Feature inventory'!$J$2:$J$130,$B11) | D11: =COUNTIF('Feature inventory'!$L$2:$L$130,$B11) | E11: Cut from the public repo before it goes live.
B12: Delete | C12: =COUNTIF('Feature inventory'!$J$2:$J$130,$B12) | D12: =COUNTIF('Feature inventory'!$L$2:$L$130,$B12) | E12: Removed outright.
B13: Total features catalogued | C13: =COUNTA('Feature inventory'!$D$2:$D$130) | D13: =COUNTA('Feature inventory'!$L$2:$L$130) | E13: Column D of the inventory; 'Yours' counts decisions made so far.
B16: By bundle
B17: Bundle | C17: Features | D17: Keep - core | E17: Share proposed as core
B18: Core plugin | C18: =COUNTIF('Feature inventory'!$B$2:$B$130,$B18) | D18: =COUNTIFS('Feature inventory'!$B$2:$B$130,$B18,'Feature inventory'!$J$2:$J$130,"Keep - core") | E18: =IF($C18=0,0,$D18/$C18)
B19: Theme | C19: =COUNTIF('Feature inventory'!$B$2:$B$130,$B19) | D19: =COUNTIFS('Feature inventory'!$B$2:$B$130,$B19,'Feature inventory'!$J$2:$J$130,"Keep - core") | E19: =IF($C19=0,0,$D19/$C19)
B20: Voice add-on | C20: =COUNTIF('Feature inventory'!$B$2:$B$130,$B20) | D20: =COUNTIFS('Feature inventory'!$B$2:$B$130,$B20,'Feature inventory'!$J$2:$J$130,"Keep - core") | E20: =IF($C20=0,0,$D20/$C20)
B21: Graph add-on | C21: =COUNTIF('Feature inventory'!$B$2:$B$130,$B21) | D21: =COUNTIFS('Feature inventory'!$B$2:$B$130,$B21,'Feature inventory'!$J$2:$J$130,"Keep - core") | E21: =IF($C21=0,0,$D21/$C21)
B22: Delegation add-on | C22: =COUNTIF('Feature inventory'!$B$2:$B$130,$B22) | D22: =COUNTIFS('Feature inventory'!$B$2:$B$130,$B22,'Feature inventory'!$J$2:$J$130,"Keep - core") | E22: =IF($C22=0,0,$D22/$C22)
B23: Wiretap (separate product) | C23: =COUNTIF('Feature inventory'!$B$2:$B$130,$B23) | D23: =COUNTIFS('Feature inventory'!$B$2:$B$130,$B23,'Feature inventory'!$J$2:$J$130,"Keep - core") | E23: =IF($C23=0,0,$D23/$C23)
B24: OpenBiografy (separate product) | C24: =COUNTIF('Feature inventory'!$B$2:$B$130,$B24) | D24: =COUNTIFS('Feature inventory'!$B$2:$B$130,$B24,'Feature inventory'!$J$2:$J$130,"Keep - core") | E24: =IF($C24=0,0,$D24/$C24)
B25: Repo tooling | C25: =COUNTIF('Feature inventory'!$B$2:$B$130,$B25) | D25: =COUNTIFS('Feature inventory'!$B$2:$B$130,$B25,'Feature inventory'!$J$2:$J$130,"Keep - core") | E25: =IF($C25=0,0,$D25/$C25)
B28: Reading of the numbers
B29: Roughly a third of everything catalogued is a separate product (Wiretap, OpenBiografy) or personal infrastructure. Cutting it is the single biggest clarity win available, and costs nothing the launch needs.
B31: The 'Fix before launch' list is the real launch gate. The largest item on it is structural: core workspace UI currently lives in the theme, not the plugin.
B33: Feature-flagging rather than deleting keeps optionality. Nothing marked 'flag off' is bad - it is unfinished, redundant with a better feature, or too advanced for a first run.

Sheet Launch blockers
B2: Launch blockers - everything marked 'Fix before launch' or 'Delete'
B3: Ordered by what would hurt most if it shipped as-is. Sequence, not estimates - sizing is a conversation with whoever builds it.
B5: # | C5: Blocker | D5: Why it blocks | E5: Severity | F5: Your owner
B6: 1 | C6: Theme vs plugin split | D6: Core workspace UI lives in the theme. WP.org distributes plugins and themes separately, so 'install the plugin' does not currently give anyone a working product. Decide: bundle the UI into the plugin, or ship an explicit plugin+theme pair. | E6: Critical
B7: 2 | C7: Caddy basic-auth shim hardcoding 'michael' | D7: Personal server infrastructure in shippable code. Immediate rejection, and an embarrassment in a public repo. | E7: Critical
B8: 3 | C8: deploy.sh with a production server IP | D8: Public repo would expose the author's server address. | E8: Critical
B9: 4 | C9: version-check.php | D9: Directly-accessible PHP outside the WordPress bootstrap. WP.org rejects this pattern. | E9: Critical
B10: 5 | C10: Personal data in scripts/ | D10: Author's own tweet and bookmark CSVs, plus editor lock files, committed to the repo. | E10: Critical
B11: 6 | C11: REST permission_callback audit | D11: At least one endpoint uses __return_true. Every one of ~50 endpoints needs an explicit capability check. | E11: Critical
B12: 7 | C12: SortableJS + marked.js loaded from jsDelivr | D12: WP.org forbids enqueuing assets from third-party CDNs. Also leaks every visitor's IP to a third party. Bundle both locally with their licence files. | E12: Critical
B13: 8 | C13: dbDelta only runs on activation | D13: wcp_db_version is stored but never compared on update, so a plugin upgrade never migrates an existing install's schema. This breaks people silently, and only after they have data worth losing. | E13: High
B14: 9 | C14: No uninstall.php / no DB migration versioning | D14: Five custom tables are created with no cleanup path and no schema version guard. Reviewers check for this. | E14: High
B15: 10 | C15: REST lockdown filter lives in the theme | D15: A theme silently changing site-wide REST behaviour will break other plugins. Move to the plugin, scope to this namespace. | E15: High
B16: 11 | C16: AI audit log has no retention or purge | D16: Table grows unbounded and stores full prompts. It is named in readme.txt as a privacy feature, so it has to hold up. | E16: High
B17: 12 | C17: Bulk 'edit items' JSON parsing | D17: Already patched twice (see changelog). Highest blast radius of any AI action - it rewrites many items at once. | E17: High
... B28: 23 | C28: CSS state after the reverted redesign | D28: A redesign was committed then reverted. Marketing screenshots come from here - budget explicit design time. | E28: Medium
C30: Severity key: Critical = cannot publish the repo or submit to WP.org. High = will produce data loss, a security report, or a bad first review. Medium = will cost adoption but is survivable.
